Metadata-Version: 2.1
Name: nkorzh-module
Version: 0.1.0
Summary: A example Python package
Home-page: UNKNOWN
Author: Nikita Kozhukharov
Author-email: n.korzhikov@gmail.com
License: MIT
Platform: UNKNOWN
